album/__init__.py
album/distributed/__init__.py
album/distributed/argument_matching.py
album/distributed/argument_parsing.py
album/distributed/distributed_modes.py
album/distributed/mode_basic.py
album/distributed/mode_queue.py
album_distributed-0.2.0.dist-info/licenses/LICENSE
album_distributed-0.2.0.dist-info/METADATA
album_distributed-0.2.0.dist-info/WHEEL
album_distributed-0.2.0.dist-info/entry_points.txt
album_distributed-0.2.0.dist-info/top_level.txt
album_distributed-0.2.0.dist-info/RECORD
