Metadata-Version: 2.4
Name: album-distributed
Version: 0.2.0
Summary: album plugin for running a solution repeatedly and distributed
Home-page: https://gitlab.com/album-app/plugins/album-run-distributed
Author: Kyle Harrington, Jan Philipp Albrecht, Deborah Schmidt
Maintainer: Kyle Harrington, Jan Philipp Albrecht, Deborah Schmidt
Maintainer-email: album@kyleharrington.com
License: MIT
Project-URL: Source, https://gitlab.com/album-app/plugins/album-distributed
Project-URL: Tracker, https://gitlab.com/album-app/plugins/album-distributed/issues
Keywords: virtual,environments,imaging,data analysis
Platform: any
Classifier: Development Status :: 3 - Alpha
Classifier: License :: OSI Approved :: MIT License
Classifier: Operating System :: MacOS :: MacOS X
Classifier: Operating System :: Microsoft :: Windows
Classifier: Operating System :: POSIX
Classifier: Programming Language :: Python :: 3.8
Classifier: Programming Language :: Python :: 3.9
Classifier: Programming Language :: Python :: Implementation :: PyPy
Classifier: Topic :: Utilities
Requires-Python: >=3.7
License-File: LICENSE
Requires-Dist: album<0.13,>=0.9.2
Dynamic: license-file
